LICENSE
MANIFEST.in
README.md
__version__
setup.py
alembic_migrate/__init__.py
alembic_migrate/cli.py
alembic_migrate.egg-info/PKG-INFO
alembic_migrate.egg-info/SOURCES.txt
alembic_migrate.egg-info/dependency_links.txt
alembic_migrate.egg-info/entry_points.txt
alembic_migrate.egg-info/not-zip-safe
alembic_migrate.egg-info/requires.txt
alembic_migrate.egg-info/top_level.txt
alembic_migrate/templates/app/README
alembic_migrate/templates/app/alembic.ini.mako
alembic_migrate/templates/app/env.py
alembic_migrate/templates/app/script.py.mako
tests/__init__.py
tests/app.py
tests/app_compare_type1.py
tests/app_compare_type2.py
tests/app_custom_directory.py
tests/app_multidb.py
tests/test_migrate.py
tests/test_migrate_flaskcli.py
tests/test_multidb_migrate.py
tests/test_multidb_migrate_flaskcli.py