Metadata-Version: 2.1
Name: alembic-migrate
Version: 2.5.9.dev0
Summary: A framework-independent fork of flask-migrate.
Home-page: https://github.com/withmehealth/alembic-migrate
Author: Filip Dimitrovski
Author-email: filipdimitrovski22@gmail.com
License: MIT
Platform: any
Classifier: Environment :: Web Environment
Classifier: Intended Audience :: Developers
Classifier: License :: OSI Approved :: MIT License
Classifier: Operating System :: OS Independent
Classifier: Programming Language :: Python
Classifier: Programming Language :: Python :: 2
Classifier: Programming Language :: Python :: 3
Classifier: Topic :: Internet :: WWW/HTTP :: Dynamic Content
Classifier: Topic :: Software Development :: Libraries :: Python Modules
